Metadata-Version: 2.1
Name: bibcodex
Version: 1.1.7
Summary: Access, analyze, and display bibliographic information
Home-page: https://github.com/thoppe/bibcodex
Author: Travis Hoppe
Author-email: travis.hoppe+{package_name}@gmail.com
License: CC-SA
Keywords: bibliographic,publications,pubmed,NLP
Platform: UNKNOWN
Classifier: Development Status :: 4 - Beta
Classifier: Intended Audience :: Developers
Classifier: Intended Audience :: Other Audience
Classifier: Intended Audience :: Science/Research
Classifier: Topic :: Database
Classifier: Topic :: Office/Business
Classifier: Topic :: Scientific/Engineering
Classifier: Programming Language :: Python :: 3
Provides-Extra: NLP
